binni4/__init__.py
binni4/dammit.py
binni4/diagnose.py
binni4/element.py
binni4/formatter.py
binni4/testing.py
binni4/builder/__init__.py
binni4/builder/_html5lib.py
binni4/builder/_htmlparser.py
binni4/builder/_lxml.py
binni4/tests/__init__.py
binni4/tests/test_builder_registry.py
binni4/tests/test_docs.py
binni4/tests/test_html5lib.py
binni4/tests/test_htmlparser.py
binni4/tests/test_lxml.py
binni4/tests/test_soup.py
binni4/tests/test_tree.py
binni4-0.0.2.dist-info/LICENSE
binni4-0.0.2.dist-info/METADATA
binni4-0.0.2.dist-info/WHEEL
binni4-0.0.2.dist-info/top_level.txt
binni4-0.0.2.dist-info/RECORD
